ke/__init__.py
ke/asm.py
ke/compiler.py
ke/errors.py
ke/parser.py
tests/__init__.py
tests/test_api.py
tests/test_asm.py
tests/test_compiler.py
tests/test_parser.py
kleenexp-0.0.7.dist-info/LICENSE
kleenexp-0.0.7.dist-info/METADATA
kleenexp-0.0.7.dist-info/WHEEL
kleenexp-0.0.7.dist-info/entry_points.txt
kleenexp-0.0.7.dist-info/top_level.txt
kleenexp-0.0.7.dist-info/RECORD
