Metadata-Version: 2.1
Name: kleenexp
Version: 0.0.7
Summary: Modern regex syntax with a painless upgrade path
Home-page: https://github.com/sonoflilit/kleenexp
Author: Aur Saraf
Author-email: aur@sarafconsulting.com
Project-URL: Bug Tracker, https://github.com/SonOfLilit/kleenexp/issues
Keywords: regular expressions regex
Classifier: Development Status :: 3 - Alpha
Classifier: Environment :: Console
Classifier: Topic :: Software Development :: Libraries
Classifier: Topic :: Software Development :: Compilers
Classifier: Topic :: Text Editors :: Text Processing
Classifier: Topic :: Utilities
Classifier: Programming Language :: Python :: 3
Classifier: License :: OSI Approved :: MIT License
Classifier: Operating System :: OS Independent
Requires-Python: >=3.6
License-File: LICENSE
Requires-Dist: parsimonious (==0.8.1)
